{
  "name": "Sixteenth General Swedish Farming Meetings in Stockholm",
  "engraver": "A. Lindberg",
  "country": "Sweden",
  "year": "1886",
  "diameter": "58",
  "obverse": "Bust of Oscar II facing left. Pearls surround the edge of the obverse.",
  "obverse_inscriptions": [
    "OSCAR II SVERIGES OCH NORGES KONUNG",
    "A\u00b7LINDBERG"
  ],
  "reverse": "A seated woman holds a pencil in her right hand. Her left hand holds a piece of paper and is resting on the coat of arms of Sweden. Around the coat of arms are a beehive and a gear to symbolize agriculture and industry. To the left of the woman is a bush, to the right is a young tree.",
  "reverse_inscriptions": [
    "SEXTONDE ALLM\u00b7SVENSKA LANDTBRUKSM\u00d6TET 1886",
    "A. P. ANDERSSON 3.E PRIS",
    "A\u00b7L\u00b7"
  ],
  "references": [
    "Numismatiska meddelanden #75"
  ],
  "description": [
    "<p>",
    "This medal was awarded to participants of the Sixteenth General Swedish Farming Meetings in Stockholm held on July 12, 1886.",
    "This medal was awarded to A. P. Andersson for third place",
    "</p>"
  ]
}